__init__.py
migrate_neems_to_sql.py
mongo_vs_sql_query.py
neems_to_sql/__init__.py
neems_to_sql/logger.py
neems_to_sql/neems_to_sql.py
neems_to_sql/triples_to_sql.py
neem_to_sql-1.0.16.dist-info/LICENSE
neem_to_sql-1.0.16.dist-info/METADATA
neem_to_sql-1.0.16.dist-info/WHEEL
neem_to_sql-1.0.16.dist-info/entry_points.txt
neem_to_sql-1.0.16.dist-info/top_level.txt
neem_to_sql-1.0.16.dist-info/RECORD
