Metadata-Version: 2.1
Name: neem_to_sql
Version: 1.0.16
Summary: Convert NEEMs database from Mongo to SQL
Author-email: Abdelrhman Bassiouny <abassiou@uni-bremen.de>
License: GNU GENERAL PUBLIC LICENSE
Project-URL: Homepage, https://github.com/AbdelrhmanBassiouny/neem_to_sql
Keywords: query,neems,database,sql,robotics,knowledge,memories,episodic
Classifier: Programming Language :: Python :: 3
Requires-Python: >=3.8
License-File: LICENSE
Requires-Dist: ipython ==8.12.0
Requires-Dist: numpy ==1.24.1
Requires-Dist: orderedset ==2.0.3
Requires-Dist: pymongo ==4.3.3
Requires-Dist: pymysql ==1.0.3
Requires-Dist: PyYAML ==6.0
Requires-Dist: rdflib ==7.0.0
Requires-Dist: SQLAlchemy ==2.0.4
Requires-Dist: tqdm ==4.64.1
Requires-Dist: typing-extensions
